verilog/decoder/3:8.v
module decoder3to8 (
    input [2:0] a,
    output reg [7:0] y
);
    always @(*) begin
        y = 8'b00000000;
        y[a] = 1'b1;
    end
endmodule

verilog/decoder/3:8_tb.v
`timescale 1ns / 1ps

module tb_decoder3to8;

    reg [2:0] a;
    wire [7:0] y;

    // Instantiate the decoder
    decoder3to8 uut (
        .a(a),
        .y(y)
    );

    initial begin
        // Create dump file for GTKWave
        $dumpfile("decoder3to8.vcd");
        $dumpvars(0, tb_decoder3to8);

        // Apply all input combinations
        a = 3'b000; #10;
        a = 3'b001; #10;
        a = 3'b010; #10;
        a = 3'b011; #10;
        a = 3'b100; #10;
        a = 3'b101; #10;
        a = 3'b110; #10;
        a = 3'b111; #10;

        $finish;
    end

endmodule

verilog/decoder/decoder3to8.vcd
$date
	Tue Apr 29 19:44:05 2025
$end
$version
	Icarus Verilog
$end
$timescale
	1ps
$end
$scope module tb_decoder3to8 $end
$var wire 8 ! y [7:0] $end
$var reg 3 " a [2:0] $end
$scope module uut $end
$var wire 3 # a [2:0] $end
$var reg 8 $ y [7:0] $end
$upscope $end
$upscope $end
$enddefinitions $end
$comment Show the parameter values. $end
$dumpall
$end
#0
$dumpvars
b1 $
b0 #
b0 "
b1 !
$end
#10000
b10 !
b10 $
b1 "
b1 #
#20000
b100 !
b100 $
b10 "
b10 #
#30000
b1000 !
b1000 $
b11 "
b11 #
#40000
b10000 !
b10000 $
b100 "
b100 #
#50000
b100000 !
b100000 $
b101 "
b101 #
#60000
b1000000 !
b1000000 $
b110 "
b110 #
#70000
b10000000 !
b10000000 $
b111 "
b111 #
