verilog/d_ff/d_ff.v
module D_FF (
    input wire D,      // Data input
    input wire clk,    // Clock input
    input wire rst,    // Asynchronous reset
    output reg Q       // Output
);

    always @(posedge clk or posedge rst) begin
        if (rst) 
            Q <= 1'b0; // Reset Q to 0
        else 
            Q <= D;   // Assign D to Q on clock's rising edge
    end

endmodule

verilog/d_ff/d_ff_tb.v
module tb_D_FF;
    reg D;
    reg clk;
    reg rst;
    wire Q;

    // Instantiate the D Flip-Flop
    D_FF uut (
        .D(D),
        .clk(clk),
        .rst(rst),
        .Q(Q)
    );

    // Clock generation
    always #5 clk = ~clk;

    initial begin
        // Initialize signals
        clk = 0;
        rst = 1;
        D = 0;
        #10 rst = 0;  // Deassert reset

        // Apply test vectors
        #10 D = 1;
        #10 D = 0;
        #10 D = 1;
        #10 rst = 1;  // Assert reset
        #10 rst = 0;
        #10 D = 1;
        #10 D = 0;

        // Finish simulation
        #20 $finish;
    end

    // Dump waveform data
    initial begin
        $dumpfile("D_FF_tb.vcd");
        $dumpvars(0, tb_D_FF);
    end

endmodule

verilog/d_ff/D_FF_tb.vcd
$date
	Fri Mar  7 20:19:49 2025
$end
$version
	Icarus Verilog
$end
$timescale
	1s
$end
$scope module tb_D_FF $end
$var wire 1 ! Q $end
$var reg 1 " D $end
$var reg 1 # clk $end
$var reg 1 $ rst $end
$scope module uut $end
$var wire 1 " D $end
$var wire 1 # clk $end
$var wire 1 $ rst $end
$var reg 1 ! Q $end
$upscope $end
$upscope $end
$enddefinitions $end
$comment Show the parameter values. $end
$dumpall
$end
#0
$dumpvars
1$
0#
0"
0!
$end
#5
1#
#10
0#
0$
#15
1#
#20
0#
1"
#25
1!
1#
#30
0#
0"
#35
0!
1#
#40
0#
1"
#45
1!
1#
#50
0!
0#
1$
#55
1#
#60
0#
0$
#65
1!
1#
#70
0#
#75
1#
#80
0#
0"
#85
0!
1#
